{
  "version": "7",
  "dialect": "postgresql",
  "entries": [
    {
      "idx": 0,
      "version": "7",
      "when": 1773968943691,
      "tag": "0000_flippant_captain_cross",
      "breakpoints": true
    },
    {
      "idx": 1,
      "version": "7",
      "when": 1774008695004,
      "tag": "0001_cloudy_gateway",
      "breakpoints": true
    },
    {
      "idx": 2,
      "version": "7",
      "when": 1774042076818,
      "tag": "0002_thick_ultimates",
      "breakpoints": true
    },
    {
      "idx": 3,
      "version": "7",
      "when": 1774100000000,
      "tag": "0003_multiplayer_lobby",
      "breakpoints": true
    }
  ]
}